<annotation>
    <folder>Pasta_BR_Dataset</folder>
    <filename>0000002563.jpg</filename>
    <source>
        <database>Unknown</database>
    </source>
    <size>
        <width>640</width>
        <height>480</height>
        <depth>3</depth>
    </size>
    <segmented>0</segmented>
    <object>
        <name>elbow</name>
        <pose>Unspecified</pose>
        <truncated>0</truncated>
        <difficult>0</difficult>
        <bndbox>
            <xmin>291.58878504672896</xmin>
            <ymin>216.2883845126836</ymin>
            <xmax>334</xmax>
            <ymax>293</ymax>
        </bndbox>
    </object>    <object>
        <name>shell</name>
        <pose>Unspecified</pose>
        <truncated>0</truncated>
        <difficult>0</difficult>
        <bndbox>
            <xmin>310.8144192256342</xmin>
            <ymin>248.33110814419226</ymin>
            <xmax>418</xmax>
            <ymax>311</ymax>
        </bndbox>
    </object>
</annotation>
