<annotation>
    <folder>Pasta_BR_Dataset</folder>
    <filename>0000003065.jpg</filename>
    <source>
        <database>Unknown</database>
    </source>
    <size>
        <width>640</width>
        <height>480</height>
        <depth>3</depth>
    </size>
    <segmented>0</segmented>
    <object>
        <name>shell</name>
        <pose>Unspecified</pose>
        <truncated>0</truncated>
        <difficult>0</difficult>
        <bndbox>
            <xmin>261.7901828681425</xmin>
            <ymin>51.58806544754572</ymin>
            <xmax>334</xmax>
            <ymax>129</ymax>
        </bndbox>
    </object>    <object>
        <name>elbow</name>
        <pose>Unspecified</pose>
        <truncated>0</truncated>
        <difficult>0</difficult>
        <bndbox>
            <xmin>345.71703561116465</xmin>
            <ymin>92.39653512993264</ymin>
            <xmax>393</xmax>
            <ymax>157</ymax>
        </bndbox>
    </object>    <object>
        <name>shell</name>
        <pose>Unspecified</pose>
        <truncated>0</truncated>
        <difficult>0</difficult>
        <bndbox>
            <xmin>376.5158806544755</xmin>
            <ymin>48.50818094321463</ymin>
            <xmax>426</xmax>
            <ymax>162</ymax>
        </bndbox>
    </object>    <object>
        <name>shell</name>
        <pose>Unspecified</pose>
        <truncated>0</truncated>
        <difficult>0</difficult>
        <bndbox>
            <xmin>197.11260827718962</xmin>
            <ymin>60.057747834456215</ymin>
            <xmax>263</xmax>
            <ymax>146</ymax>
        </bndbox>
    </object>    <object>
        <name>elbow</name>
        <pose>Unspecified</pose>
        <truncated>0</truncated>
        <difficult>0</difficult>
        <bndbox>
            <xmin>199.42252165543795</xmin>
            <ymin>306.44850818094324</ymin>
            <xmax>248</xmax>
            <ymax>390</ymax>
        </bndbox>
    </object>
</annotation>
