<annotation>
    <folder>Pasta_BR_Dataset</folder>
    <filename>0000000317.jpg</filename>
    <source>
        <database>Unknown</database>
    </source>
    <size>
        <width>640</width>
        <height>480</height>
        <depth>3</depth>
    </size>
    <segmented>0</segmented>
    <object>
        <name>elbow</name>
        <pose>Unspecified</pose>
        <truncated>0</truncated>
        <difficult>0</difficult>
        <bndbox>
            <xmin>521.4953271028038</xmin>
            <ymin>327.6368491321762</ymin>
            <xmax>607</xmax>
            <ymax>388</ymax>
        </bndbox>
    </object>    <object>
        <name>penne</name>
        <pose>Unspecified</pose>
        <truncated>0</truncated>
        <difficult>0</difficult>
        <bndbox>
            <xmin>547.9305740987984</xmin>
            <ymin>208.27770360480642</ymin>
            <xmax>639</xmax>
            <ymax>280</ymax>
        </bndbox>
    </object>
</annotation>
