<annotation>
    <folder>Pasta_BR_Dataset</folder>
    <filename>0000003423.jpg</filename>
    <source>
        <database>Unknown</database>
    </source>
    <size>
        <width>640</width>
        <height>480</height>
        <depth>3</depth>
    </size>
    <segmented>0</segmented>
    <object>
        <name>penne</name>
        <pose>Unspecified</pose>
        <truncated>0</truncated>
        <difficult>0</difficult>
        <bndbox>
            <xmin>444.3699357362392</xmin>
            <ymin>1</ymin>
            <xmax>456</xmax>
            <ymax>12</ymax>
        </bndbox>
    </object>    <object>
        <name>penne</name>
        <pose>Unspecified</pose>
        <truncated>0</truncated>
        <difficult>0</difficult>
        <bndbox>
            <xmin>430.9583682592903</xmin>
            <ymin>1</ymin>
            <xmax>447</xmax>
            <ymax>57</ymax>
        </bndbox>
    </object>
</annotation>
