<annotation>
    <folder>Pasta_BR_Dataset</folder>
    <filename>0000000778.jpg</filename>
    <source>
        <database>Unknown</database>
    </source>
    <size>
        <width>640</width>
        <height>480</height>
        <depth>3</depth>
    </size>
    <segmented>0</segmented>
    <object>
        <name>shell</name>
        <pose>Unspecified</pose>
        <truncated>0</truncated>
        <difficult>0</difficult>
        <bndbox>
            <xmin>119.87850151873103</xmin>
            <ymin>264.86668916638547</ymin>
            <xmax>211</xmax>
            <ymax>393</ymax>
        </bndbox>
    </object>    <object>
        <name>shell</name>
        <pose>Unspecified</pose>
        <truncated>0</truncated>
        <difficult>0</difficult>
        <bndbox>
            <xmin>25.109686128923393</xmin>
            <ymin>360.4454944313197</ymin>
            <xmax>166</xmax>
            <ymax>438</ymax>
        </bndbox>
    </object>    <object>
        <name>shell</name>
        <pose>Unspecified</pose>
        <truncated>0</truncated>
        <difficult>0</difficult>
        <bndbox>
            <xmin>1</xmin>
            <ymin>87.47890651366859</ymin>
            <xmax>50</xmax>
            <ymax>133</ymax>
        </bndbox>
    </object>    <object>
        <name>elbow</name>
        <pose>Unspecified</pose>
        <truncated>0</truncated>
        <difficult>0</difficult>
        <bndbox>
            <xmin>220.3172460344246</xmin>
            <ymin>239.75700303746206</ymin>
            <xmax>306</xmax>
            <ymax>303</ymax>
        </bndbox>
    </object>
</annotation>
