<annotation>
    <folder>Pasta_BR_Dataset</folder>
    <filename>0000002790.jpg</filename>
    <source>
        <database>Unknown</database>
    </source>
    <size>
        <width>640</width>
        <height>480</height>
        <depth>3</depth>
    </size>
    <segmented>0</segmented>
    <object>
        <name>penne</name>
        <pose>Unspecified</pose>
        <truncated>0</truncated>
        <difficult>0</difficult>
        <bndbox>
            <xmin>220.96822096822098</xmin>
            <ymin>1</ymin>
            <xmax>246</xmax>
            <ymax>32</ymax>
        </bndbox>
    </object>    <object>
        <name>shell</name>
        <pose>Unspecified</pose>
        <truncated>0</truncated>
        <difficult>0</difficult>
        <bndbox>
            <xmin>312.2067122067122</xmin>
            <ymin>362.10276210276214</ymin>
            <xmax>378</xmax>
            <ymax>479</ymax>
        </bndbox>
    </object>    <object>
        <name>elbow</name>
        <pose>Unspecified</pose>
        <truncated>0</truncated>
        <difficult>0</difficult>
        <bndbox>
            <xmin>205.2866052866053</xmin>
            <ymin>415.56281556281556</ymin>
            <xmax>267</xmax>
            <ymax>479</ymax>
        </bndbox>
    </object>    <object>
        <name>penne</name>
        <pose>Unspecified</pose>
        <truncated>0</truncated>
        <difficult>0</difficult>
        <bndbox>
            <xmin>227.3834273834274</xmin>
            <ymin>1.4256014256014258</ymin>
            <xmax>309</xmax>
            <ymax>68</ymax>
        </bndbox>
    </object>
</annotation>
