<annotation>
    <folder>Pasta_BR_Dataset</folder>
    <filename>0000002028.jpg</filename>
    <source>
        <database>Unknown</database>
    </source>
    <size>
        <width>640</width>
        <height>480</height>
        <depth>3</depth>
    </size>
    <segmented>0</segmented>
    <object>
        <name>elbow</name>
        <pose>Unspecified</pose>
        <truncated>0</truncated>
        <difficult>0</difficult>
        <bndbox>
            <xmin>115.61230412071968</xmin>
            <ymin>333.60417875798026</ymin>
            <xmax>204</xmax>
            <ymax>399</ymax>
        </bndbox>
    </object>    <object>
        <name>shell</name>
        <pose>Unspecified</pose>
        <truncated>0</truncated>
        <difficult>0</difficult>
        <bndbox>
            <xmin>133.0237957051654</xmin>
            <ymin>402.5536854323854</ymin>
            <xmax>242</xmax>
            <ymax>462</ymax>
        </bndbox>
    </object>    <object>
        <name>shell</name>
        <pose>Unspecified</pose>
        <truncated>0</truncated>
        <difficult>0</difficult>
        <bndbox>
            <xmin>35.5194428322693</xmin>
            <ymin>391.4103308183401</ymin>
            <xmax>160</xmax>
            <ymax>461</ymax>
        </bndbox>
    </object>    <object>
        <name>shell</name>
        <pose>Unspecified</pose>
        <truncated>0</truncated>
        <difficult>0</difficult>
        <bndbox>
            <xmin>25.072547881601857</xmin>
            <ymin>71.0388856645386</ymin>
            <xmax>106</xmax>
            <ymax>123</ymax>
        </bndbox>
    </object>
</annotation>
