<annotation>
    <folder>Pasta_BR_Dataset</folder>
    <filename>0000001188.jpg</filename>
    <source>
        <database>Unknown</database>
    </source>
    <size>
        <width>640</width>
        <height>480</height>
        <depth>3</depth>
    </size>
    <segmented>0</segmented>
    <object>
        <name>elbow</name>
        <pose>Unspecified</pose>
        <truncated>0</truncated>
        <difficult>0</difficult>
        <bndbox>
            <xmin>589.6726290921364</xmin>
            <ymin>157.9480256496794</ymin>
            <xmax>639</xmax>
            <ymax>243</ymax>
        </bndbox>
    </object>    <object>
        <name>elbow</name>
        <pose>Unspecified</pose>
        <truncated>0</truncated>
        <difficult>0</difficult>
        <bndbox>
            <xmin>467.3641579480257</xmin>
            <ymin>187.91765102936216</ymin>
            <xmax>531</xmax>
            <ymax>272</ymax>
        </bndbox>
    </object>    <object>
        <name>elbow</name>
        <pose>Unspecified</pose>
        <truncated>0</truncated>
        <difficult>0</difficult>
        <bndbox>
            <xmin>167.66790415119814</xmin>
            <ymin>284.30644616942294</ymin>
            <xmax>255</xmax>
            <ymax>344</ymax>
        </bndbox>
    </object>    <object>
        <name>shell</name>
        <pose>Unspecified</pose>
        <truncated>0</truncated>
        <difficult>0</difficult>
        <bndbox>
            <xmin>1</xmin>
            <ymin>82.61896726290922</ymin>
            <xmax>63</xmax>
            <ymax>141</ymax>
        </bndbox>
    </object>    <object>
        <name>elbow</name>
        <pose>Unspecified</pose>
        <truncated>0</truncated>
        <difficult>0</difficult>
        <bndbox>
            <xmin>1</xmin>
            <ymin>198.44751940600744</ymin>
            <xmax>53</xmax>
            <ymax>286</ymax>
        </bndbox>
    </object>    <object>
        <name>shell</name>
        <pose>Unspecified</pose>
        <truncated>0</truncated>
        <difficult>0</difficult>
        <bndbox>
            <xmin>86.66891663854203</xmin>
            <ymin>92.33884576442796</ymin>
            <xmax>179</xmax>
            <ymax>143</ymax>
        </bndbox>
    </object>
</annotation>
