<annotation>
    <folder>Pasta_BR_Dataset</folder>
    <filename>0000002699.jpg</filename>
    <source>
        <database>Unknown</database>
    </source>
    <size>
        <width>640</width>
        <height>480</height>
        <depth>3</depth>
    </size>
    <segmented>0</segmented>
    <object>
        <name>elbow</name>
        <pose>Unspecified</pose>
        <truncated>0</truncated>
        <difficult>0</difficult>
        <bndbox>
            <xmin>219.54261954261955</xmin>
            <ymin>110.48411048411049</ymin>
            <xmax>274</xmax>
            <ymax>165</ymax>
        </bndbox>
    </object>    <object>
        <name>shell</name>
        <pose>Unspecified</pose>
        <truncated>0</truncated>
        <difficult>0</difficult>
        <bndbox>
            <xmin>372.0819720819721</xmin>
            <ymin>9.266409266409267</ymin>
            <xmax>435</xmax>
            <ymax>103</ymax>
        </bndbox>
    </object>    <object>
        <name>elbow</name>
        <pose>Unspecified</pose>
        <truncated>0</truncated>
        <difficult>0</difficult>
        <bndbox>
            <xmin>255.8954558954559</xmin>
            <ymin>332.8779328779329</ymin>
            <xmax>307</xmax>
            <ymax>414</ymax>
        </bndbox>
    </object>    <object>
        <name>tortellini</name>
        <pose>Unspecified</pose>
        <truncated>0</truncated>
        <difficult>0</difficult>
        <bndbox>
            <xmin>364.24116424116426</xmin>
            <ymin>205.2866052866053</ymin>
            <xmax>463</xmax>
            <ymax>295</ymax>
        </bndbox>
    </object>    <object>
        <name>tortellini</name>
        <pose>Unspecified</pose>
        <truncated>0</truncated>
        <difficult>0</difficult>
        <bndbox>
            <xmin>290.82269082269084</xmin>
            <ymin>1</ymin>
            <xmax>386</xmax>
            <ymax>45</ymax>
        </bndbox>
    </object>
</annotation>
