<annotation>
    <folder>Pasta_BR_Dataset</folder>
    <filename>0000001571.jpg</filename>
    <source>
        <database>Unknown</database>
    </source>
    <size>
        <width>640</width>
        <height>480</height>
        <depth>3</depth>
    </size>
    <segmented>0</segmented>
    <object>
        <name>shell</name>
        <pose>Unspecified</pose>
        <truncated>0</truncated>
        <difficult>0</difficult>
        <bndbox>
            <xmin>23.54978354978355</xmin>
            <ymin>74.11255411255412</ymin>
            <xmax>106</xmax>
            <ymax>124</ymax>
        </bndbox>
    </object>    <object>
        <name>shell</name>
        <pose>Unspecified</pose>
        <truncated>0</truncated>
        <difficult>0</difficult>
        <bndbox>
            <xmin>132.2943722943723</xmin>
            <ymin>403.1168831168832</ymin>
            <xmax>244</xmax>
            <ymax>462</ymax>
        </bndbox>
    </object>    <object>
        <name>shell</name>
        <pose>Unspecified</pose>
        <truncated>0</truncated>
        <difficult>0</difficult>
        <bndbox>
            <xmin>1</xmin>
            <ymin>72.72727272727273</ymin>
            <xmax>32</xmax>
            <ymax>124</ymax>
        </bndbox>
    </object>    <object>
        <name>shell</name>
        <pose>Unspecified</pose>
        <truncated>0</truncated>
        <difficult>0</difficult>
        <bndbox>
            <xmin>34.63203463203463</xmin>
            <ymin>387.1861471861472</ymin>
            <xmax>162</xmax>
            <ymax>463</ymax>
        </bndbox>
    </object>
</annotation>
